arc_core/__init__.py
arc_core/arc_core.py
arc_core/model_configs.py
arc_core/teaching_packs.py
arc_core/cli/__init__.py
arc_core/cli/arc.py
metisos_arc_core-1.2.2.dist-info/METADATA
metisos_arc_core-1.2.2.dist-info/WHEEL
metisos_arc_core-1.2.2.dist-info/entry_points.txt
metisos_arc_core-1.2.2.dist-info/top_level.txt
metisos_arc_core-1.2.2.dist-info/RECORD
