Metadata-Version: 2.4
Name: metisos-arc-core
Version: 1.2.2
Summary: Adaptive Recursive Consciousness (ARC) Core - A framework for continual learning AI systems
Home-page: https://github.com/metisos/arc-core
Author: MetisOS
Author-email: cjohnson@metisos.com
Keywords: artificial intelligence,deep learning,transformers,continual learning,lora,neural networks,reasoning,memory
Classifier: Development Status :: 4 - Beta
Classifier: Intended Audience :: Science/Research
Classifier: License :: OSI Approved :: MIT License
Classifier: Programming Language :: Python :: 3.8
Classifier: Programming Language :: Python :: 3.9
Classifier: Programming Language :: Python :: 3.10
Classifier: Programming Language :: Python :: 3.11
Classifier: Programming Language :: Python :: 3.12
Classifier: Topic :: Scientific/Engineering :: Artificial Intelligence
Classifier: Topic :: Scientific/Engineering
Classifier: Topic :: Software Development :: Libraries :: Python Modules
Requires-Python: >=3.8
Requires-Dist: torch>=2.0.0
Requires-Dist: transformers>=4.25.0
Requires-Dist: peft>=0.6.0
Requires-Dist: numpy>=1.24.0
Requires-Dist: datasets>=2.14.0
Requires-Dist: tokenizers>=0.14.0
Requires-Dist: accelerate>=0.20.0
Requires-Dist: sentencepiece>=0.1.99
Requires-Dist: protobuf>=3.20.0
Requires-Dist: huggingface-hub>=0.16.0
Requires-Dist: safetensors>=0.3.0
Requires-Dist: packaging>=23.0
Requires-Dist: pyyaml>=6.0
Requires-Dist: regex>=2023.0.0
Requires-Dist: requests>=2.31.0
Requires-Dist: tqdm>=4.65.0
Requires-Dist: filelock>=3.12.0
Dynamic: author
Dynamic: author-email
Dynamic: classifier
Dynamic: description
Dynamic: description-content-type
Dynamic: home-page
Dynamic: keywords
Dynamic: requires-dist
Dynamic: requires-python
Dynamic: summary
